{
    "version": 1,
    "disable_existing_loggers": false,
    "loggers": {
        "root": {
            "handlers": ["console"],
            "level": "INFO"
        },
        "main": {
            "handlers": ["console", "file"],
            "level": "INFO",
            "qualname": "main",
            "propagate": 0
        }
    },
    "handlers": {
        "console": {
            "class": "logging.StreamHandler",
            "level": "DEBUG",
            "formatter": "console"
        },
        "file": {
            "class": "logging.FileHandler",
            "level": "WARNING",
            "formatter": "file",
            "filename": "log_file_name",
            "mode": "a"
        }
    },
    "formatters": {
        "console": {
            "format": "%(asctime)s - %(name)s - %(levelname)s - %(message)s"
        },
        "file": {
            "format": "%(asctime)s - %(name)s - %(levelname)s - %(funcName)s - %(message)s"
        }
    }
}